main.py
questioning_game-0.3.0.dist-info/licenses/LICENSE
questioning_game-0.3.0.dist-info/METADATA
questioning_game-0.3.0.dist-info/WHEEL
questioning_game-0.3.0.dist-info/entry_points.txt
questioning_game-0.3.0.dist-info/top_level.txt
questioning_game-0.3.0.dist-info/RECORD
