Metadata-Version: 2.4
Name: Questioning_game
Version: 0.3.0
Summary: A game that asks question and award you prize on every correct answer just a question game to practice my coding skills and its does not really award you money for real. its a fake game made for fun and learning.
Author-email: Aliyan Khan <aliyankhan25552@gmail.com.com>
License: MIT
Project-URL: Homepage, https://github.com/sHadow-987
Project-URL: Repository, https://github.com/sHadow-987/Questioning_game
Requires-Python: >=3.7
License-File: LICENSE
Dynamic: license-file
